rstobj/__init__.py
rstobj/_version.py
rstobj/base.py
rstobj/demo.py
rstobj/option.py
rstobj/directives/__init__.py
rstobj/directives/base.py
rstobj/directives/codeblock.py
rstobj/directives/image.py
rstobj/directives/miscellaneous.py
rstobj/directives/table.py
rstobj/directives/toc.py
rstobj/docs/__init__.py
rstobj/markup/__init__.py
rstobj/markup/bullet_list.py
rstobj/markup/enum_list.py
rstobj/markup/header.py
rstobj/markup/hyperlink.py
rstobj/templates/__init__.py
rstobj/templates/rstobj.directives.base.Directive.rst
rstobj/templates/rstobj.directives.codeblock.Code.rst
rstobj/templates/rstobj.directives.codeblock.CodeBlockBase.rst
rstobj/templates/rstobj.directives.codeblock.CodeBlockEmpty.rst
rstobj/templates/rstobj.directives.image.Image.rst
rstobj/templates/rstobj.directives.miscellaneous.Include.rst
rstobj/templates/rstobj.directives.table.ListTable.rst
rstobj/templates/rstobj.directives.toc.TableOfContent.rst
rstobj/templates/rstobj.markup.bullet_list.BulletList.rst
rstobj/templates/rstobj.markup.enum_list.EnumList.rst
rstobj/templates/rstobj.markup.header.Header.rst
rstobj/templates/rstobj.markup.hyperlink.Reference.rst
rstobj/templates/rstobj.markup.hyperlink.URI.rst
rstobj/tests/__init__.py
rstobj/tests/rstobj.directives.codeblock.Code.render-indent.rst
rstobj/tests/rstobj.directives.codeblock.CodeBlock.render.rst
rstobj/tests/rstobj.directives.codeblock.CodeBlockEmpty.render-indent.rst
rstobj/tests/rstobj.directives.codeblock.CodeBlockEmpty.render.rst
rstobj/tests/rstobj.directives.codeblock.CodeBlockPython.render.rst
rstobj/tests/rstobj.directives.image.Image.render-indent.rst
rstobj/tests/rstobj.directives.image.Image.uri-only.rst
rstobj/tests/rstobj.directives.image.Image.with-everything.rst
rstobj/tests/rstobj.directives.miscellaneous.Include.render.rst
rstobj/tests/rstobj.directives.table.ListTable.with-codeblock-indent.rst
rstobj/tests/rstobj.directives.table.ListTable.with-codeblock.rst
rstobj-1.2.1.dist-info/AUTHORS.rst
rstobj-1.2.1.dist-info/LICENSE.txt
rstobj-1.2.1.dist-info/METADATA
rstobj-1.2.1.dist-info/WHEEL
rstobj-1.2.1.dist-info/top_level.txt
rstobj-1.2.1.dist-info/RECORD
